eagle/__init__.py
eagle/__main__.py
eagle/eagle.py
eagle/groups.py
eagle/meta.py
eagle/storage.py
eagle/tasks.py
eagle/tools.py
eagle_cli-0.5.dist-info/LICENSE
eagle_cli-0.5.dist-info/METADATA
eagle_cli-0.5.dist-info/WHEEL
eagle_cli-0.5.dist-info/entry_points.txt
eagle_cli-0.5.dist-info/top_level.txt
eagle_cli-0.5.dist-info/RECORD
