Metadata-Version: 2.1
Name: eagle-cli
Version: 0.5
Summary: Simple TODO tool for CLI.
Home-page: https://github.com/im-n1/eagle
Author: n1
License: UNKNOWN
Platform: UNKNOWN
Classifier: Environment :: Console
Classifier: Programming Language :: Python :: 3.6
Classifier: Intended Audience :: End Users/Desktop
Classifier: License :: OSI Approved :: MIT License
Classifier: Programming Language :: Python :: 3 :: Only
Classifier: Topic :: Office/Business :: Scheduling 
Requires-Python: >=3.6
